
{
  "Logging": {
    "LogLevel": {
      "Default": "Debug",
      "Microsoft.AspNetCore": "Information",
      "Microsoft.EntityFrameworkCore.Database.Command": "Information"
    }
  },
  "ConnectionStrings": {
    "DefaultConnection": "Server=(localdb)\\mssqllocaldb;Database=CorchEdgesDev;Trusted_Connection=true;MultipleActiveResultSets=true",
    "CacheConnection": "localhost:6379"
  },
  "ExternalServices": {
    "ApiBaseUrl": "https://dev-api.example.com",
    "ApiKey": "dev-api-key-placeholder",
    "Timeout": "00:00:30"
  },
  "Features": {
    "EnableDetailedErrors": true,
    "EnableSwagger": true,
    "EnableSeedData": true
  },
  "Email": {
    "SmtpServer": "localhost",
    "SmtpPort": 587,
    "Username": "dev-email@example.com",
    "Password": "dev-email-password-placeholder",
    "EnableSsl": false
  },
  "Security": {
    "JwtSecret": "dev-jwt-secret-key-placeholder",
    "TokenExpirationMinutes": 60
  }
}